universal_llm/__init__.py
universal_llm/base.py
universal_llm/cli.py
universal_llm/config.py
universal_llm/models.py
universal_llm/registry.py
universal_llm/settings.py
universal_llm/adapters/__init__.py
universal_llm/adapters/anthropic.py
universal_llm/adapters/ollama.py
universal_llm/adapters/openai.py
universal_llm-0.2.0.dist-info/METADATA
universal_llm-0.2.0.dist-info/WHEEL
universal_llm-0.2.0.dist-info/entry_points.txt
universal_llm-0.2.0.dist-info/RECORD
