Metadata-Version: 2.4
Name: universal-llm
Version: 0.2.0
Summary: Minimal universal LLM client - swap providers with one env var
Author-email: Ian McLaughlin <ian.mclaughlin@prizeout.com>
Requires-Python: >=3.9
Requires-Dist: httpx>=0.24.0
Requires-Dist: pydantic-settings>=2.0.0
Requires-Dist: pydantic>=2.0.0
Requires-Dist: python-dotenv>=1.0.0
Requires-Dist: rich>=13.0.0
Requires-Dist: typer>=0.9.0
Provides-Extra: all
Provides-Extra: dev
Requires-Dist: pytest-asyncio>=0.21.0; extra == 'dev'
Requires-Dist: pytest>=7.0.0; extra == 'dev'
Requires-Dist: vcrpy>=5.0.0; extra == 'dev'
